screentronic/Client.py
screentronic/UdpInterface.py
screentronic/__init__.py
screentronic/directControl/Blind.py
screentronic/directControl/ControlTronic.py
screentronic/directControl/__init__.py
screentronic/directControl/st2134/ST2134.py
screentronic/directControl/st2134/__init__.py
screentronic/smartControl/SmartBlind.py
screentronic/smartControl/SmartControl.py
screentronic/smartControl/__init__.py
screentronic-0.1.0.dist-info/LICENSE
screentronic-0.1.0.dist-info/METADATA
screentronic-0.1.0.dist-info/WHEEL
screentronic-0.1.0.dist-info/RECORD
