Metadata-Version: 2.1
Name: screentronic
Version: 0.1.0
Summary: A python library for interfacing with ScreenTronic blinds by CONTROLtronic via IP
License: BSD-4-Clause
Author: Simon Billemont
Author-email: simon@angelcorp.be
Requires-Python: >=3.9,<4.0
Classifier: License :: Other/Proprietary License
Classifier: Programming Language :: Python :: 3
Classifier: Programming Language :: Python :: 3.9
Classifier: Programming Language :: Python :: 3.10
Classifier: Programming Language :: Python :: 3.11
Requires-Dist: asyncio-dgram (>=2.1,<3.0)
Requires-Dist: cachetools (>=5,<6)
